Metadata-Version: 2.1
Name: goeffel
Version: 0.3.0
Summary: Measures the resource utilization of a specific process over time
Home-page: https://github.com/jgehrcke/goeffel
Author: Dr. Jan-Philip Gehrcke
Author-email: jgehrcke@googlemail.com
License: UNKNOWN
Platform: UNKNOWN
Classifier: License :: OSI Approved :: MIT License
Classifier: Programming Language :: Python
Classifier: Programming Language :: Python :: 3.6
Classifier: Programming Language :: Python :: 3.7
Classifier: Programming Language :: Python :: Implementation :: CPython
Classifier: Operating System :: POSIX
